para/__init__.py
para/about.py
para/map.py
para/tests/__init__.py
para/tests/test_map.py
para-0.0.8.dist-info/LICENSE
para-0.0.8.dist-info/METADATA
para-0.0.8.dist-info/WHEEL
para-0.0.8.dist-info/top_level.txt
para-0.0.8.dist-info/RECORD
