Metadata-Version: 1.1
Name: para
Version: 0.0.8
Summary: a set utilities that ake advantage of python's 'multiprocessing' module to distribute CPU-intensive tasks
Home-page: https://github.com/halfak/para
Author: Aaron Halfaker
Author-email: aaron.halfaker@gmail.com
License: MIT
Platform: UNKNOWN
Classifier: Programming Language :: Python
Classifier: Programming Language :: Python :: 3
Classifier: Programming Language :: Python :: 3 :: Only
Classifier: Environment :: Other Environment
Classifier: Intended Audience :: Developers
Classifier: License :: OSI Approved :: MIT License
Classifier: Operating System :: OS Independent
Classifier: Topic :: Software Development :: Libraries :: Python Modules
Classifier: Topic :: Utilities
Classifier: Topic :: Scientific/Engineering
